pyincore_incubator/__init__.py
pyincore_incubator/globals.py
pyincore_incubator/logging.ini
pyincore_incubator/analyses/__init__.py
pyincore_incubator/analyses/electricpowernetworkrecovery/__init__.py
pyincore_incubator/analyses/electricpowernetworkrecovery/electricpowernetworkrecovery.py
pyincore_incubator/analyses/example/__init__.py
pyincore_incubator/analyses/example/example.py
pyincore_incubator/analyses/independentrecovery/__init__.py
pyincore_incubator/analyses/independentrecovery/independentrecovery.py
pyincore_incubator-0.1.0.dist-info/licenses/LICENSE
pyincore_incubator-0.1.0.dist-info/METADATA
pyincore_incubator-0.1.0.dist-info/WHEEL
pyincore_incubator-0.1.0.dist-info/top_level.txt
pyincore_incubator-0.1.0.dist-info/RECORD
