Metadata-Version: 2.4
Name: pyincore_incubator
Version: 0.1.0
Summary: IN-CORE analysis incubator python package
Home-page: https://incore.ncsa.illinois.edu
License: Mozilla Public License v2.0
Project-URL: Bug Reports, https://github.com/IN-CORE/pyincore-incubator/issues
Project-URL: Source, https://github.com/IN-CORE/pyincore-incubator
Keywords: infrastructure,resilience,hazards,data discovery,IN-CORE,earthquake,tsunami,tornado,hurricane,dislocation
Classifier: Development Status :: 4 - Beta
Classifier: Intended Audience :: Science/Research
Classifier: License :: OSI Approved :: Mozilla Public License 2.0 (MPL 2.0)
Classifier: Natural Language :: English
Classifier: Operating System :: OS Independent
Classifier: Programming Language :: Python :: 3
Classifier: Topic :: Scientific/Engineering
Requires-Python: >=3.9
License-File: LICENSE
Requires-Dist: pyincore
Provides-Extra: test
Requires-Dist: pycodestyle>=2.6.0; extra == "test"
Requires-Dist: pytest>=3.9.0; extra == "test"
Requires-Dist: python-jose>=3.0; extra == "test"
Dynamic: classifier
Dynamic: description
Dynamic: description-content-type
Dynamic: home-page
Dynamic: keywords
Dynamic: license
Dynamic: license-file
Dynamic: project-url
Dynamic: provides-extra
Dynamic: requires-dist
Dynamic: requires-python
Dynamic: summary
